jrdb/__init__.py
jrdb/client.py
jrdb/data/base.py
jrdb/model.py
jrdb/parser.py
jrdb/repo.py
jrdb/schema/__init__.py
jrdb/schema/bac.py
jrdb/schema/cha.py
jrdb/schema/cyb.py
jrdb/schema/cza.py
jrdb/schema/hjc.py
jrdb/schema/joa.py
jrdb/schema/kab.py
jrdb/schema/kka.py
jrdb/schema/kta.py
jrdb/schema/kyi.py
jrdb/schema/kza.py
jrdb/schema/ot.py
jrdb/schema/ou.py
jrdb/schema/ow.py
jrdb/schema/oz.py
jrdb/schema/sed.py
jrdb/schema/skb.py
jrdb/schema/srb.py
jrdb/schema/tyb.py
jrdb/schema/ukc.py
jrdb/urlcodec.py
jrdb/writer.py
jrdb-0.2.0.dist-info/WHEEL
jrdb-0.2.0.dist-info/METADATA
jrdb-0.2.0.dist-info/RECORD
