Metadata-Version: 2.1
Name: jrdb
Version: 0.2.0
Summary: 
Author: otomarukanta
Author-email: kanta208@gmail.com
Requires-Python: >=3.7,<4.0
Classifier: Programming Language :: Python :: 3
Classifier: Programming Language :: Python :: 3.7
Requires-Dist: fastavro (>=0.21.18,<0.22.0)
Requires-Dist: google-cloud-storage (>=1.13,<2.0)
Requires-Dist: lxml (>=4.3,<5.0)
Requires-Dist: requests (>=2.21,<3.0)
